odoo/addons/maintenance_request_purchase/README.rst
odoo/addons/maintenance_request_purchase/__init__.py
odoo/addons/maintenance_request_purchase/__manifest__.py
odoo/addons/maintenance_request_purchase/i18n/ca.po
odoo/addons/maintenance_request_purchase/i18n/es.po
odoo/addons/maintenance_request_purchase/i18n/fr.po
odoo/addons/maintenance_request_purchase/i18n/it.po
odoo/addons/maintenance_request_purchase/i18n/maintenance_request_purchase.pot
odoo/addons/maintenance_request_purchase/models/__init__.py
odoo/addons/maintenance_request_purchase/models/maintenance_request.py
odoo/addons/maintenance_request_purchase/models/purchase_order.py
odoo/addons/maintenance_request_purchase/readme/CONTRIBUTORS.rst
odoo/addons/maintenance_request_purchase/readme/DESCRIPTION.rst
odoo/addons/maintenance_request_purchase/static/description/icon.png
odoo/addons/maintenance_request_purchase/static/description/index.html
odoo/addons/maintenance_request_purchase/tests/__init__.py
odoo/addons/maintenance_request_purchase/tests/test_maintenance_purchase.py
odoo/addons/maintenance_request_purchase/views/maintenance_request.xml
odoo/addons/maintenance_request_purchase/views/purchase_order_views.xml
odoo13_addon_maintenance_request_purchase-13.0.1.0.1.dev3.dist-info/METADATA
odoo13_addon_maintenance_request_purchase-13.0.1.0.1.dev3.dist-info/WHEEL
odoo13_addon_maintenance_request_purchase-13.0.1.0.1.dev3.dist-info/top_level.txt
odoo13_addon_maintenance_request_purchase-13.0.1.0.1.dev3.dist-info/RECORD
