Metadata-Version: 2.1
Name: odoo13-addon-maintenance_request_purchase
Version: 13.0.1.0.1.dev3
Summary: Allows you to link PO with maintenance requests
Home-page: https://github.com/OCA/maintenance
Author: CreuBlanca,Dixmit,Odoo Community Association (OCA)
Author-email: support@odoo-community.org
License: AGPL-3
Classifier: Programming Language :: Python
Classifier: Framework :: Odoo
Classifier: Framework :: Odoo :: 13.0
Classifier: License :: OSI Approved :: GNU Affero General Public License v3
Requires-Python: >=3.5
Requires-Dist: odoo13-addon-base-maintenance
Requires-Dist: odoo<13.1dev,>=13.0a
